.gitignore
MANIFEST.in
README.rst
setup.cfg
setup.py
docs/HISTORY.txt
docs/LICENSE.GPL
docs/LICENSE.txt
docs/MANUAL.txt
raptus/__init__.py
raptus.article.default.egg-info/PKG-INFO
raptus.article.default.egg-info/SOURCES.txt
raptus.article.default.egg-info/dependency_links.txt
raptus.article.default.egg-info/entry_points.txt
raptus.article.default.egg-info/namespace_packages.txt
raptus.article.default.egg-info/not-zip-safe
raptus.article.default.egg-info/requires.txt
raptus.article.default.egg-info/top_level.txt
raptus/article/__init__.py
raptus/article/default/__init__.py
raptus/article/default/configure.zcml
raptus/article/default/overrides.zcml
raptus/article/default/setuphandlers.py
raptus/article/default/profiles/default/import_steps.xml
raptus/article/default/profiles/default/metadata.xml
raptus/article/default/profiles/default/raptus.article.default_install.txt
raptus/article/default/profiles/default/viewlets.xml