Metadata-Version: 1.1
Name: raptus.article.default
Version: 2.0b13
Summary: Default configuration of the raptus.article package.
Home-page: https://github.com/Raptus/raptus.article.default
Author: Raptus AG
Author-email: dev@raptus.com
License: GPL
Platform: UNKNOWN
Classifier: Programming Language :: Python
Classifier: Topic :: Software Development :: Libraries :: Python Modules
